{"stat.walkOneCm":71976,"stat.pickup.minecraft.bone":1,"stat.useItem.minecraft.torch":3,"stat.playerKills":1,"stat.pickup.minecraft.stick":4,"stat.pickup.minecraft.wooden_axe":1,"stat.pickup.minecraft.gravel":16,"stat.pickup.minecraft.crafting_table":2,"stat.craftItem.minecraft.cooked_porkchop":5,"stat.pickup.minecraft.stone_pickaxe":3,"stat.useItem.minecraft.cobblestone":70,"stat.craftItem.minecraft.crafting_table":2,"stat.furnaceInteraction":6,"stat.pickup.minecraft.flint":2,"stat.pickup.minecraft.stone_axe":1,"stat.useItem.minecraft.gravel":6,"stat.drop.minecraft.dirt":1,"stat.useItem.minecraft.cooked_porkchop":3,"stat.mineBlock.minecraft.coal_ore":6,"stat.pickup.minecraft.log":10,"stat.craftItem.minecraft.leather_helmet":1,"stat.jump":336,"stat.pickup.minecraft.coal":13,"stat.fallOneCm":5636,"stat.pickup.minecraft.beef":7,"stat.pickup.minecraft.furnace":1,"stat.pickup.minecraft.porkchop":3,"stat.pickup.minecraft.stone":1,"stat.crouchOneCm":2311,"stat.pickup.minecraft.spider_eye":2,"stat.pickup.minecraft.leather_helmet":1,"stat.craftItem.minecraft.torch":4,"stat.pickup.minecraft.dirt":34,"stat.useItem.minecraft.dirt":22,"stat.sprintOneCm":70568,"stat.useItem.minecraft.stone_slab2":17,"stat.pickup.minecraft.cooked_beef":7,"stat.craftItem.minecraft.stick":8,"stat.craftItem.minecraft.wooden_axe":1,"stat.craftingTableInteraction":6,"stat.pickup.minecraft.rotten_flesh":5,"stat.craftItem.minecraft.furnace":1,"stat.craftItem.minecraft.planks":40,"stat.craftItem.minecraft.stone_axe":1,"stat.pickup.minecraft.wooden_pickaxe":3,"stat.damageTaken":620,"stat.pickup.minecraft.leather":5,"stat.mineBlock.minecraft.crafting_table":1,"stat.craftItem.minecraft.stone_pickaxe":1,"stat.useItem.minecraft.wooden_pickaxe":17,"stat.craftItem.minecraft.cooked_beef":1,"stat.pickup.minecraft.cobblestone":208,"stat.mobKills":4,"stat.mineBlock.minecraft.log":10,"stat.craftItem.minecraft.wooden_door":3,"stat.useItem.minecraft.beef":3,"stat.pickup.minecraft.planks":25,"stat.useItem.minecraft.wooden_door":2,"stat.flyOneCm":30505,"stat.deaths":1,"stat.drop":1,"stat.mineBlock.minecraft.leaves":5,"stat.playOneMinute":26962,"stat.mineBlock.minecraft.gravel":14,"stat.useItem.minecraft.stone_pickaxe":118,"stat.useItem.minecraft.cooked_beef":1,"stat.sneakTime":858,"stat.damageDealt":637,"stat.timeSinceDeath":8254,"stat.useItem.minecraft.wooden_axe":31,"stat.killEntity.Cow":3,"stat.mineBlock.minecraft.dirt":32,"stat.killEntity.Pig":1,"stat.craftItem.minecraft.wooden_pickaxe":1,"stat.mineBlock.minecraft.stone":127,"stat.mineBlock.minecraft.tallgrass":9}